dhcppython/__init__.py
dhcppython/client.py
dhcppython/exceptions.py
dhcppython/options.py
dhcppython/packet.py
dhcppython/utils.py
dhcppython/runtime_assets/__init__.py
dhcppython/runtime_assets/options.csv
dhcppython/runtime_assets/oui.txt
dhcppython-0.1.3.dist-info/LICENSE
dhcppython-0.1.3.dist-info/METADATA
dhcppython-0.1.3.dist-info/WHEEL
dhcppython-0.1.3.dist-info/top_level.txt
dhcppython-0.1.3.dist-info/RECORD
