Metadata-Version: 2.1
Name: dhcppython
Version: 0.1.3
Summary: ('Package for working with DHCP packets - including a DHCP client',)
Home-page: https://github.com/vfrazao-ns1/dhcppython
Author: Victor Frazao
Author-email: 
License: Apache 2.0
Platform: UNKNOWN
Classifier: License :: OSI Approved :: Apache Software License
Classifier: Programming Language :: Python
Classifier: Programming Language :: Python :: 3
Classifier: Programming Language :: Python :: 3.8
Classifier: Programming Language :: Python :: Implementation :: CPython
Requires-Python: >=3.8.0
